ens/__init__.py
ens/abis.py
ens/constants.py
ens/main.py
ens/registrar.py
ens/utils.py
ens-0.6.0.dist-info/DESCRIPTION.rst
ens-0.6.0.dist-info/METADATA
ens-0.6.0.dist-info/RECORD
ens-0.6.0.dist-info/WHEEL
ens-0.6.0.dist-info/metadata.json
ens-0.6.0.dist-info/top_level.txt
