Metadata-Version: 2.0
Name: ens
Version: 0.6.0
Summary: Ethereum Name Service, made easy in Python
Home-page: https://github.com/carver/ens.py
Author: Jason Carver
Author-email: ut96caarrs@snkmail.com
License: MIT
Keywords: ethereum eth web3 web3.py ENS
Platform: UNKNOWN
Classifier: Development Status :: 4 - Beta
Classifier: Intended Audience :: Information Technology
Classifier: Topic :: Database :: Front-Ends
Classifier: Topic :: Internet :: Finger
Classifier: Topic :: Internet :: Name Service (DNS)
Classifier: Topic :: Security :: Cryptography
Classifier: Topic :: System :: Distributed Computing
Classifier: Topic :: System :: Systems Administration :: Authentication/Directory
Classifier: Topic :: Utilities
Classifier: License :: OSI Approved :: MIT License
Classifier: Programming Language :: Python :: 3
Classifier: Programming Language :: Python :: 3.5
Requires-Python: >=3.5
Requires-Dist: pytz
Requires-Dist: web3 (<4,>=3.16.1)
